bread/__init__.py
bread/apps.py
bread/auth.py
bread/context_processors.py
bread/dynamic_preferences_registry.py
bread/formatters.py
bread/menu.py
bread/middleware.py
bread/urls.py
bread/contrib/__init__.py
bread/contrib/languages/__init__.py
bread/contrib/languages/fields.py
bread/contrib/languages/languages.py
bread/contrib/languages/regenerate.py
bread/contrib/reports/__init__.py
bread/contrib/reports/apps.py
bread/contrib/reports/models.py
bread/contrib/reports/urls.py
bread/contrib/reports/views.py
bread/contrib/reports/migrations/0001_initial.py
bread/contrib/reports/migrations/0002_auto_20210322_1115.py
bread/contrib/reports/migrations/0003_report_custom_queryset.py
bread/contrib/reports/migrations/0004_auto_20210619_1502.py
bread/contrib/reports/migrations/0005_auto_20210826_1951.py
bread/contrib/reports/migrations/__init__.py
bread/contrib/workflows/__init__.py
bread/contrib/workflows/apps.py
bread/contrib/workflows/settings.py
bread/contrib/workflows/views.py
bread/contrib/workflows/management/__init__.py
bread/contrib/workflows/management/commands/__init__.py
bread/contrib/workflows/management/commands/activity_diagram.py
bread/contrib/workflows/management/commands/dot_diagram.py
bread/contrib/workflows/models/__init__.py
bread/contrib/workflows/models/base.py
bread/contrib/workflows/models/nodes.py
bread/forms/__init__.py
bread/forms/fields.py
bread/forms/forms.py
bread/layout/__init__.py
bread/layout/base.py
bread/layout/skeleton.py
bread/layout/components/__init__.py
bread/layout/components/button.py
bread/layout/components/content_switcher.py
bread/layout/components/datatable.py
bread/layout/components/grid.py
bread/layout/components/icon.py
bread/layout/components/loading.py
bread/layout/components/modal.py
bread/layout/components/notification.py
bread/layout/components/overflow_menu.py
bread/layout/components/pagination.py
bread/layout/components/progress_indicator.py
bread/layout/components/search.py
bread/layout/components/shell_header.py
basx_bread-0.4.58.dist-info/LICENSE
basx_bread-0.4.58.dist-info/LICENSE.carbon
basx_bread-0.4.58.dist-info/METADATA
basx_bread-0.4.58.dist-info/WHEEL
basx_bread-0.4.58.dist-info/top_level.txt
basx_bread-0.4.58.dist-info/RECORD
