Metadata-Version: 2.1
Name: basx-bread
Version: 0.4.58
Summary: Engine to create database applications based on Django and the IBM Carbon Design System
Home-page: https://github.com/basxsoftwareassociation/bread
Author: basx Software Association
Author-email: sam@basx.dev
License: New BSD License
Platform: UNKNOWN
Classifier: Development Status :: 3 - Alpha
Classifier: Environment :: Console
Classifier: Environment :: Web Environment
Classifier: Intended Audience :: Developers
Classifier: License :: OSI Approved :: BSD License
Classifier: Programming Language :: Python
Classifier: Programming Language :: Python :: 3 :: Only
License-File: LICENSE
License-File: LICENSE.carbon
Requires-Dist: Django
Requires-Dist: python-dateutil
Requires-Dist: htmlgenerator
Requires-Dist: django-extensions
Requires-Dist: django-guardian
Requires-Dist: django-dynamic-preferences
Requires-Dist: django-countries
Requires-Dist: django-money[exchange]
Requires-Dist: django-phonenumber-field
Requires-Dist: phonenumbers
Requires-Dist: django-simple-history
Requires-Dist: openpyxl
Requires-Dist: djangoql
Requires-Dist: requests
Requires-Dist: celery
Requires-Dist: django-celery-results
Requires-Dist: django-haystack
Requires-Dist: celery-haystack-ng
Requires-Dist: whoosh
Requires-Dist: WeasyPrint
Requires-Dist: backports.zoneinfo ; python_version < "3.9"
Provides-Extra: testing
Requires-Dist: hypothesis[django] ; extra == 'testing'
Requires-Dist: django-dynamic-fixture ; extra == 'testing'
